README.rst
setup.py
flytrap/__init__.py
flytrap/comments/__init__.py
flytrap/comments/admin.py
flytrap/comments/apps.py
flytrap/comments/filter.py
flytrap/comments/models.py
flytrap/comments/serializers.py
flytrap/comments/tests.py
flytrap/comments/urls.py
flytrap/comments/views.py
flytrap/comments/migrations/0001_initial.py
flytrap/comments/migrations/0002_auto_20180328_1648.py
flytrap/comments/migrations/__init__.py
flytrap_comments.egg-info/PKG-INFO
flytrap_comments.egg-info/SOURCES.txt
flytrap_comments.egg-info/dependency_links.txt
flytrap_comments.egg-info/requires.txt
flytrap_comments.egg-info/top_level.txt