Metadata-Version: 1.1
Name: flytrap-comments
Version: 0.0.1
Summary: A simple Django app to comment
Home-page: https://github.com/flytrap/flytrap-comments
Author: flytrap
Author-email: hiddenstat@gmial.com
License: UNKNOWN
Platform: UNKNOWN
Classifier: Development Status :: 4 - Beta
Classifier: Environment :: Web Environment
Classifier: Framework :: Django
Classifier: Intended Audience :: Developers
Classifier: License :: OSI Approved :: MIT License
Classifier: Operating System :: OS Independent
Classifier: Programming Language :: Python
Classifier: Programming Language :: Python :: 2
Classifier: Topic :: Software Development :: Libraries :: Python Modules
